robotic_transformer_pytorch/__init__.py
robotic_transformer_pytorch/robotic_transformer_pytorch.py
robotic_transformer_pytorch-0.2.3.dist-info/LICENSE
robotic_transformer_pytorch-0.2.3.dist-info/METADATA
robotic_transformer_pytorch-0.2.3.dist-info/WHEEL
robotic_transformer_pytorch-0.2.3.dist-info/top_level.txt
robotic_transformer_pytorch-0.2.3.dist-info/RECORD
