Metadata-Version: 2.1
Name: robotic-transformer-pytorch
Version: 0.2.3
Summary: Robotic Transformer - Pytorch
Home-page: https://github.com/lucidrains/robotic-transformer-pytorch
Author: Phil Wang
Author-email: lucidrains@gmail.com
License: MIT
Keywords: artificial intelligence,deep learning,transformers,attention mechanism,robotics
Classifier: Development Status :: 4 - Beta
Classifier: Intended Audience :: Developers
Classifier: Topic :: Scientific/Engineering :: Artificial Intelligence
Classifier: License :: OSI Approved :: MIT License
Classifier: Programming Language :: Python :: 3.6
License-File: LICENSE
Requires-Dist: classifier-free-guidance-pytorch >=0.7.1
Requires-Dist: einops >=0.8
Requires-Dist: torch >=2.0
